elvis/__init__.py
elvis/battery.py
elvis/charging_event.py
elvis/charging_event_generator.py
elvis/charging_point.py
elvis/charging_station.py
elvis/config.py
elvis/distribution.py
elvis/infrastructure_node.py
elvis/main.py
elvis/result.py
elvis/set_up_infrastructure.py
elvis/simulate.py
elvis/units.py
elvis/vehicle.py
elvis/waiting_queue.py
elvis/sched/__init__.py
elvis/sched/schedulers.py
elvis/utility/__init__.py
elvis/utility/elvis_general.py
elvis/utility/walker.py
py_elvis-0.2.1.dist-info/LICENSE
py_elvis-0.2.1.dist-info/METADATA
py_elvis-0.2.1.dist-info/WHEEL
py_elvis-0.2.1.dist-info/top_level.txt
py_elvis-0.2.1.dist-info/RECORD
