Metadata-Version: 2.1
Name: py-elvis
Version: 0.2.1
Summary: A planning and management tool for electric vehicles charging infrastructure
Home-page: 
Author: Moritz Markschläger, Jonas Zell, Marcus Voss, Mahmoud Draz, and Izgh Hadachi
Author-email: moritz.markschlaeger@dai-labor.de
License: UNKNOWN
Platform: UNKNOWN
Classifier: Programming Language :: Python :: 3
Classifier: License :: OSI Approved :: MIT License
Classifier: Operating System :: OS Independent
Requires-Python: >=3.6
License-File: LICENSE
